api/__init__.py
api/dns_manager.py
api/get_ip.py
api/logs.py
esddns_service/__init__.py
esddns_service/esddns_endpoint.py
tests/__init__.py
tests/test_daemon_happy.py
tests/test_daemon_un_authed_bad_svc.py
tests/test_daemon_un_authed_good_svc.py
esddns-0.0.1.dist-info/LICENSE
esddns-0.0.1.dist-info/METADATA
esddns-0.0.1.dist-info/WHEEL
esddns-0.0.1.dist-info/top_level.txt
esddns-0.0.1.dist-info/RECORD
