Metadata-Version: 2.1
Name: esddns
Version: 0.0.1
Summary: Open Source Dynamic DNS
Author: Aziz Kurbanov
Author-email: aziz@platformrnd.com
License: MIT License
Project-URL: issue_tracker, https://github.com/sqe/esddns/issues
Project-URL: repository, https://github.com/sqe/esddns
Keywords: dyndns,dynamicdns,dns,dynamic
Classifier: License :: OSI Approved :: MIT License
Classifier: Operating System :: OS Independent
Classifier: Programming Language :: Python :: 3
License-File: LICENSE
